pymdmix_solvent/__init__.py
pymdmix_solvent/solvent.py
pymdmix_solvent-0.0.3.data/data/pymdmix/pymdmix_solvent.yml
pymdmix_solvent-0.0.3.dist-info/LICENSE
pymdmix_solvent-0.0.3.dist-info/METADATA
pymdmix_solvent-0.0.3.dist-info/WHEEL
pymdmix_solvent-0.0.3.dist-info/top_level.txt
pymdmix_solvent-0.0.3.dist-info/RECORD
